fmcore/__init__.py
fmcore/algorithm/__init__.py
fmcore/algorithm/bedrock.py
fmcore/algorithm/langchain.py
fmcore/algorithm/sentence_transformers.py
fmcore/algorithm/vllm.py
fmcore/algorithm/huggingface/__init__.py
fmcore/algorithm/huggingface/transformers.py
fmcore/algorithm/sklearn/SklearnSGDClassifier.py
fmcore/algorithm/sklearn/SklearnSGDRegressor.py
fmcore/algorithm/sklearn/__init__.py
fmcore/constants/_AlgorithmConstants.py
fmcore/constants/_MetricConstants.py
fmcore/constants/_TaskConstants.py
fmcore/constants/_VisualizationConstants.py
fmcore/constants/__init__.py
fmcore/data/__init__.py
fmcore/data/reader.py
fmcore/data/writer.py
fmcore/framework/__init__.py
fmcore/framework/_algorithm.py
fmcore/framework/_dataset.py
fmcore/framework/_metric.py
fmcore/framework/_predictions.py
fmcore/framework/_task_mixins.py
fmcore/framework/_visualize.py
fmcore/framework/_chain/Chain.py
fmcore/framework/_chain/__init__.py
fmcore/framework/_evaluator/AccelerateEvaluator.py
fmcore/framework/_evaluator/Evaluator.py
fmcore/framework/_evaluator/LocalEvaluator.py
fmcore/framework/_evaluator/RayEvaluator.py
fmcore/framework/_evaluator/__init__.py
fmcore/framework/_task/__init__.py
fmcore/framework/_task/classification.py
fmcore/framework/_task/dense_retrieval.py
fmcore/framework/_task/embedding.py
fmcore/framework/_task/ranking.py
fmcore/framework/_task/regression.py
fmcore/framework/_task/retrieval.py
fmcore/framework/_task/sparse_retrieval.py
fmcore/framework/_task/text_generation.py
fmcore/framework/_tracker/AimTracker.py
fmcore/framework/_tracker/LogFileTracker.py
fmcore/framework/_tracker/Tracker.py
fmcore/framework/_tracker/__init__.py
fmcore/framework/_trainer/AccelerateTrainer.py
fmcore/framework/_trainer/LocalTrainer.py
fmcore/framework/_trainer/RayTuneTrainer.py
fmcore/framework/_trainer/Trainer.py
fmcore/framework/_trainer/__init__.py
fmcore/framework/dl/__init__.py
fmcore/framework/dl/torch/__init__.py
fmcore/framework/dl/torch/_torch_base.py
fmcore-0.1.5.2.dist-info/METADATA
fmcore-0.1.5.2.dist-info/WHEEL
fmcore-0.1.5.2.dist-info/licenses/LICENSE
fmcore-0.1.5.2.dist-info/RECORD
