Metadata-Version: 2.4
Name: fmcore
Version: 0.1.5.2
Summary: A specialized toolkit for scaling experimental research with Foundation Models.
Author-email: Abhishek Divekar <adivekar@utexas.edu>
License-File: LICENSE
Classifier: Operating System :: OS Independent
Classifier: Programming Language :: Python :: 3
Requires-Python: >=3.11
Requires-Dist: autoenum==1.0.2
Requires-Dist: bears==0.1.6
Requires-Dist: pyyaml==6.0.2
Requires-Dist: requests==2.32.3
Requires-Dist: urllib3==2.3.0
Provides-Extra: all
Requires-Dist: accelerate; extra == 'all'
Requires-Dist: aim==3.*; extra == 'all'
Requires-Dist: altair; extra == 'all'
Requires-Dist: bears[all]; extra == 'all'
Requires-Dist: bitsandbytes; extra == 'all'
Requires-Dist: bokeh; extra == 'all'
Requires-Dist: brotli; extra == 'all'
Requires-Dist: dask; extra == 'all'
Requires-Dist: dask[complete]; extra == 'all'
Requires-Dist: datasets; extra == 'all'
Requires-Dist: deepspeed; extra == 'all'
Requires-Dist: einops; extra == 'all'
Requires-Dist: evaluate; extra == 'all'
Requires-Dist: faiss-cpu; extra == 'all'
Requires-Dist: gpustat; extra == 'all'
Requires-Dist: holoviews; extra == 'all'
Requires-Dist: hvplot>=0.10.0; extra == 'all'
Requires-Dist: imageio; extra == 'all'
Requires-Dist: matplotlib; extra == 'all'
Requires-Dist: mauve-text; extra == 'all'
Requires-Dist: nltk; extra == 'all'
Requires-Dist: nvitop; extra == 'all'
Requires-Dist: orjson; extra == 'all'
Requires-Dist: plotly; extra == 'all'
Requires-Dist: plotly-express; extra == 'all'
Requires-Dist: pytest; extra == 'all'
Requires-Dist: ray; extra == 'all'
Requires-Dist: ray[default]; extra == 'all'
Requires-Dist: ray[serve]; extra == 'all'
Requires-Dist: ray[tune]; extra == 'all'
Requires-Dist: safetensors; extra == 'all'
Requires-Dist: seaborn; extra == 'all'
Requires-Dist: sentence-transformers; extra == 'all'
Requires-Dist: sentencepiece; extra == 'all'
Requires-Dist: tensorboard; extra == 'all'
Requires-Dist: tiktoken; extra == 'all'
Requires-Dist: tokenizers; extra == 'all'
Requires-Dist: torch; extra == 'all'
Requires-Dist: transformers>=4.42.4; extra == 'all'
Requires-Dist: wandb; extra == 'all'
